tk_config_tools/__init__.py
tk_config_tools/account_config.py
tk_config_tools/add_config.py
tk_config_tools/config_request.py
tk_config_tools/config_util.py
tk_config_tools/get_config.py
utils/__init__.py
utils/config_util.py
utils/date_util.py
utils/file_util.py
tk_config_tools-1.0.2.dist-info/METADATA
tk_config_tools-1.0.2.dist-info/WHEEL
tk_config_tools-1.0.2.dist-info/top_level.txt
tk_config_tools-1.0.2.dist-info/RECORD
