Metadata-Version: 2.1
Name: tk-config-tools
Version: 1.0.2
Summary: 统一配置获取sdk
Author: @niudawang
Author-email: your@email.com
